pyscf_ac0-0.1.0.dist-info/RECORD
pyscf_ac0-0.1.0.dist-info/WHEEL
pyscf_ac0-0.1.0.dist-info/entry_points.txt
pyscf_ac0-0.1.0.dist-info/METADATA
pyscf_ac0-0.1.0.dist-info/licenses/LICENSE
pyscf_ac0.dylibs/libgfortran.5.dylib
pyscf_ac0.dylibs/libquadmath.0.dylib
pyscf_ac0.dylibs/libgcc_s.1.1.dylib
pyscf/cas_ac0/_version.py
pyscf/cas_ac0/ac0_lib.cpython-311-darwin.so
pyscf/cas_ac0/_cli.py
pyscf/cas_ac0/__init__.py
pyscf/cas_ac0/accas.py
