Metadata-Version: 2.1
Name: pyscf-ac0
Version: 0.1.0
Summary: Interface to and port of fragments of GAMMCOR code developed by Pernal group at Lodz University of Technology
License:                     GNU GENERAL PUBLIC LICENSE
Requires-Python: <3.13,>=3.10
Requires-Dist: pyscf>=2.4.0
Requires-Dist: numpy
